{
    "bug_report_url": "https://github.com/h8d13/archinstoo",
    "script": "guided",
    "archinstoo-language": "English",
    "bootloader_config": {
        "bootloader": "Grub",
        "uki": true,
        "removable": true
    },
    "kernels": [
        "linux-zen"
    ],
    "kernel_headers": true,
    "init_hooks": "systemd",
    "disk_config": {
        "config_type": "default_layout",
        "device_modifications": [
            {
                "device": "/dev/nvme0n1",
                "wipe": true,
                "partitions": [
                    {
                        "obj_id": "5539394a-042e-4ac3-8861-57ca670bfd4f",
                        "status": "create",
                        "type": "primary",
                        "start": {
                            "value": 1,
                            "unit": "MiB",
                            "sector_size": {
                                "value": 512,
                                "unit": "B"
                            }
                        },
                        "size": {
                            "value": 1,
                            "unit": "GiB",
                            "sector_size": {
                                "value": 512,
                                "unit": "B"
                            }
                        },
                        "fs_type": "fat32",
                        "mountpoint": "/boot",
                        "mount_options": [],
                        "flags": [
                            "boot",
                            "esp"
                        ],
                        "dev_path": null,
                        "btrfs": []
                    },
                    {
                        "obj_id": "6454f1e1-5744-40ce-93f3-1a746c3d4d74",
                        "status": "create",
                        "type": "primary",
                        "start": {
                            "value": 1074790400,
                            "unit": "B",
                            "sector_size": {
                                "value": 512,
                                "unit": "B"
                            }
                        },
                        "size": {
                            "value": 499031998464,
                            "unit": "B",
                            "sector_size": {
                                "value": 512,
                                "unit": "B"
                            }
                        },
                        "fs_type": "btrfs",
                        "mountpoint": null,
                        "mount_options": [
                            "compress=zstd"
                        ],
                        "flags": [],
                        "dev_path": null,
                        "btrfs": [
                            {
                                "name": "@",
                                "mountpoint": "/"
                            },
                            {
                                "name": "@home",
                                "mountpoint": "/home"
                            },
                            {
                                "name": "@log",
                                "mountpoint": "/var/log"
                            },
                            {
                                "name": "@pkg",
                                "mountpoint": "/var/cache/pacman/pkg"
                            }
                        ]
                    }
                ]
            }
        ],
        "lvm_config": {
            "config_type": "default",
            "vol_groups": [
                {
                    "name": "ArchinstallVg",
                    "lvm_pvs": [
                        "6454f1e1-5744-40ce-93f3-1a746c3d4d74"
                    ],
                    "volumes": [
                        {
                            "obj_id": "e82fd144-c371-4140-a846-1a1f3f9546e1",
                            "status": "create",
                            "name": "root",
                            "fs_type": "btrfs",
                            "length": {
                                "value": 46,
                                "unit": "GiB",
                                "sector_size": {
                                    "value": 512,
                                    "unit": "B"
                                }
                            },
                            "mountpoint": "/",
                            "mount_options": [
                                "compress=zstd"
                            ],
                            "btrfs": [
                                {
                                    "name": "@",
                                    "mountpoint": "/"
                                },
                                {
                                    "name": "@home",
                                    "mountpoint": "/home"
                                },
                                {
                                    "name": "@log",
                                    "mountpoint": "/var/log"
                                },
                                {
                                    "name": "@pkg",
                                    "mountpoint": "/var/cache/pacman/pkg"
                                }
                            ]
                        }
                    ]
                }
            ]
        },
        "btrfs_options": {
            "snapshot_config": {
                "type": "Timeshift"
            }
        }
    },
    "auth_config": {
        "lock_root_account": true,
        "privilege_escalation": "doas",
        "users": [
            {
                "username": "myuser",
                "enc_password": null,
                "elev": true,
                "groups": null,
                "shell": "bash"
            }
        ]
    },
    "locale_config": {
        "kb_layout": "us",
        "sys_lang": "en_US.UTF-8",
        "sys_enc": "UTF-8",
        "console_font": "default8x16"
    },
    "pacman_config": {
        "mirror_regions": {
            "Germany": [
                "https://frankfurt.mirror.pkgbuild.com/$repo/os/$arch",
                "https://berlin.mirror.pkgbuild.com/$repo/os/$arch"
            ]
        },
        "custom_servers": [],
        "optional_repositories": [
            "multilib"
        ],
        "custom_repositories": [
            {
                "name": "evoquus",
                "url": "https://evoquus.com/pkgs/",
                "sign_check": "Never",
                "sign_option": "TrustAll"
            }
        ],
        "pacman_options": [
            "Color",
            "ILoveCandy"
        ]
    },
    "swap": {
        "enabled": true,
        "algorithm": "lz4"
    },
    "profile_config": {
        "profiles": [
            {
                "main": "Desktop",
                "details": [
                    "KDE Plasma"
                ],
                "custom_settings": {
                    "KDE Plasma": {}
                }
            },
            {
                "main": "Server",
                "details": [
                    "Docker",
                    "Sshd"
                ],
                "custom_settings": {}
            }
        ],
        "gfx_driver": "Intel (open-source)",
        "greeter": "gdm"
    },
    "hostname": "archinstoo",
    "app_config": {
        "bluetooth_config": {
            "enabled": true
        },
        "audio_config": {
            "audio": "pipewire"
        },
        "print_service_config": {
            "enabled": true
        },
        "firewall_config": {
            "firewall": "ufw"
        },
        "management_config": {
            "tools": [
                "git",
                "man-db",
                "pacman-contrib"
            ]
        },
        "monitor_config": {
            "monitor": "bottom"
        },
        "editor_config": {
            "editor": "micro"
        },
        "power_management_config": {
            "power_management": "power-profiles-daemon"
        },
        "security_config": {
            "tools": [
                "fail2ban"
            ]
        }
    },
    "network_config": {
        "type": "nm_iwd"
    },
    "timezone": "Europe/Berlin",
    "ntp": true,
    "packages": [
        "syncthing",
        "chromium"
    ],
    "aur_packages": [
        "nvidia-580xx-utils"
    ],
    "services": [
        "sshd",
        {"unit": "syncthing.service", "user": "myuser", "linger": true}
    ],
    "custom_commands": [
        "#arch-chroot via bash tmp files # lines are ignored",
        "#ex: su - user -c \"bash ~/.stash/repo/install.sh\""
    ]
}
